{
    "data": {
        "color1": [
            {
                "id": 1,
                "coordinates": {
                    "x": 0.312,
                    "y": 0.5412,
                    "Y": 30.5
                }
            },
            {
                "id": 2,
                "coordinates": {
                    "x": 0.312,
                    "y": 0.5412,
                    "Y": 30.5
                }
            },
            {
                "id": 3,
                "coordinates": {
                    "x": 0.2952,
                    "y": 0.4786,
                    "Y": 29.96
                }
            },
            {
                "id": 4,
                "coordinates": {
                    "x": 0.2952,
                    "y": 0.4786,
                    "Y": 29.96
                }
            },
            {
                "id": 5,
                "coordinates": {
                    "x": 0.2952,
                    "y": 0.4786,
                    "Y": 29.96
                }
            },
            {
                "id": 6,
                "coordinates": {
                    "x": 0.3466,
                    "y": 0.4899,
                    "Y": 29.28
                }
            },
            {
                "id": 7,
                "coordinates": {
                    "x": 0.3466,
                    "y": 0.4899,
                    "Y": 29.28
                }
            },
            {
                "id": 8,
                "coordinates": {
                    "x": 0.3466,
                    "y": 0.4899,
                    "Y": 29.28
                }
            },
            {
                "id": 9,
                "coordinates": {
                    "x": 0.3949,
                    "y": 0.4897,
                    "Y": 27.15
                }
            },
            {
                "id": 10,
                "coordinates": {
                    "x": 0.3949,
                    "y": 0.4897,
                    "Y": 27.15
                }
            },
            {
                "id": 11,
                "coordinates": {
                    "x": 0.2627,
                    "y": 0.4254,
                    "Y": 29.58
                }
            },
            {
                "id": 12,
                "coordinates": {
                    "x": 0.2627,
                    "y": 0.4254,
                    "Y": 29.58
                }
            },
            {
                "id": 13,
                "coordinates": {
                    "x": 0.2627,
                    "y": 0.4254,
                    "Y": 29.58
                }
            },
            {
                "id": 14,
                "coordinates": {
                    "x": 0.3039,
                    "y": 0.4358,
                    "Y": 27.84
                }
            },
            {
                "id": 15,
                "coordinates": {
                    "x": 0.3039,
                    "y": 0.4358,
                    "Y": 27.84
                }
            },
            {
                "id": 16,
                "coordinates": {
                    "x": 0.3039,
                    "y": 0.4358,
                    "Y": 27.84
                }
            },
            {
                "id": 17,
                "coordinates": {
                    "x": 0.355,
                    "y": 0.4477,
                    "Y": 27.16
                }
            },
            {
                "id": 18,
                "coordinates": {
                    "x": 0.355,
                    "y": 0.4477,
                    "Y": 27.16
                }
            },
            {
                "id": 19,
                "coordinates": {
                    "x": 0.355,
                    "y": 0.4477,
                    "Y": 27.16
                }
            },
            {
                "id": 20,
                "coordinates": {
                    "x": 0.3933,
                    "y": 0.4506,
                    "Y": 25.06
                }
            },
            {
                "id": 21,
                "coordinates": {
                    "x": 0.3933,
                    "y": 0.4506,
                    "Y": 25.06
                }
            },
            {
                "id": 22,
                "coordinates": {
                    "x": 0.3933,
                    "y": 0.4506,
                    "Y": 25.06
                }
            },
            {
                "id": 23,
                "coordinates": {
                    "x": 0.4469,
                    "y": 0.4595,
                    "Y": 26.79
                }
            },
            {
                "id": 24,
                "coordinates": {
                    "x": 0.4469,
                    "y": 0.4595,
                    "Y": 26.79
                }
            },
            {
                "id": 25,
                "coordinates": {
                    "x": 0.2376,
                    "y": 0.3652,
                    "Y": 29.51
                }
            },
            {
                "id": 26,
                "coordinates": {
                    "x": 0.2376,
                    "y": 0.3652,
                    "Y": 29.51
                }
            },
            {
                "id": 27,
                "coordinates": {
                    "x": 0.2376,
                    "y": 0.3652,
                    "Y": 29.51
                }
            },
            {
                "id": 28,
                "coordinates": {
                    "x": 0.2747,
                    "y": 0.3785,
                    "Y": 28.26
                }
            },
            {
                "id": 29,
                "coordinates": {
                    "x": 0.2747,
                    "y": 0.3785,
                    "Y": 28.26
                }
            },
            {
                "id": 30,
                "coordinates": {
                    "x": 0.2747,
                    "y": 0.3785,
                    "Y": 28.26
                }
            },
            {
                "id": 31,
                "coordinates": {
                    "x": 0.3159,
                    "y": 0.3928,
                    "Y": 27.56
                }
            },
            {
                "id": 32,
                "coordinates": {
                    "x": 0.3159,
                    "y": 0.3928,
                    "Y": 27.56
                }
            },
            {
                "id": 33,
                "coordinates": {
                    "x": 0.3159,
                    "y": 0.3928,
                    "Y": 27.56
                }
            },
            {
                "id": 34,
                "coordinates": {
                    "x": 0.3616,
                    "y": 0.4073,
                    "Y": 28.68
                }
            },
            {
                "id": 35,
                "coordinates": {
                    "x": 0.3616,
                    "y": 0.4073,
                    "Y": 28.68
                }
            },
            {
                "id": 36,
                "coordinates": {
                    "x": 0.3616,
                    "y": 0.4073,
                    "Y": 28.68
                }
            },
            {
                "id": 37,
                "coordinates": {
                    "x": 0.4025,
                    "y": 0.4161,
                    "Y": 27.55
                }
            },
            {
                "id": 38,
                "coordinates": {
                    "x": 0.4025,
                    "y": 0.4161,
                    "Y": 27.55
                }
            },
            {
                "id": 39,
                "coordinates": {
                    "x": 0.4025,
                    "y": 0.4161,
                    "Y": 27.55
                }
            },
            {
                "id": 40,
                "coordinates": {
                    "x": 0.4475,
                    "y": 0.4224,
                    "Y": 27.3
                }
            },
            {
                "id": 41,
                "coordinates": {
                    "x": 0.4475,
                    "y": 0.4224,
                    "Y": 27.3
                }
            },
            {
                "id": 42,
                "coordinates": {
                    "x": 0.4475,
                    "y": 0.4224,
                    "Y": 27.3
                }
            },
            {
                "id": 43,
                "coordinates": {
                    "x": 0.4833,
                    "y": 0.4221,
                    "Y": 26.54
                }
            },
            {
                "id": 44,
                "coordinates": {
                    "x": 0.4833,
                    "y": 0.4221,
                    "Y": 26.54
                }
            },
            {
                "id": 45,
                "coordinates": {
                    "x": 0.2305,
                    "y": 0.3215,
                    "Y": 30.03
                }
            },
            {
                "id": 46,
                "coordinates": {
                    "x": 0.2305,
                    "y": 0.3215,
                    "Y": 30.03
                }
            },
            {
                "id": 47,
                "coordinates": {
                    "x": 0.2531,
                    "y": 0.3311,
                    "Y": 29.53
                }
            },
            {
                "id": 48,
                "coordinates": {
                    "x": 0.2531,
                    "y": 0.3311,
                    "Y": 29.53
                }
            },
            {
                "id": 49,
                "coordinates": {
                    "x": 0.2531,
                    "y": 0.3311,
                    "Y": 29.53
                }
            },
            {
                "id": 50,
                "coordinates": {
                    "x": 0.2863,
                    "y": 0.3418,
                    "Y": 28.39
                }
            },
            {
                "id": 51,
                "coordinates": {
                    "x": 0.2863,
                    "y": 0.3418,
                    "Y": 28.39
                }
            },
            {
                "id": 52,
                "coordinates": {
                    "x": 0.2863,
                    "y": 0.3418,
                    "Y": 28.39
                }
            },
            {
                "id": 53,
                "coordinates": {
                    "x": 0.3247,
                    "y": 0.3584,
                    "Y": 28.84
                }
            },
            {
                "id": 54,
                "coordinates": {
                    "x": 0.3247,
                    "y": 0.3584,
                    "Y": 28.84
                }
            },
            {
                "id": 55,
                "coordinates": {
                    "x": 0.3247,
                    "y": 0.3584,
                    "Y": 28.84
                }
            },
            {
                "id": 56,
                "coordinates": {
                    "x": 0.3627,
                    "y": 0.3704,
                    "Y": 28.75
                }
            },
            {
                "id": 57,
                "coordinates": {
                    "x": 0.3627,
                    "y": 0.3704,
                    "Y": 28.75
                }
            },
            {
                "id": 58,
                "coordinates": {
                    "x": 0.3627,
                    "y": 0.3704,
                    "Y": 28.75
                }
            },
            {
                "id": 59,
                "coordinates": {
                    "x": 0.4068,
                    "y": 0.384,
                    "Y": 28.21
                }
            },
            {
                "id": 60,
                "coordinates": {
                    "x": 0.4068,
                    "y": 0.384,
                    "Y": 28.21
                }
            },
            {
                "id": 61,
                "coordinates": {
                    "x": 0.4068,
                    "y": 0.384,
                    "Y": 28.21
                }
            },
            {
                "id": 62,
                "coordinates": {
                    "x": 0.4459,
                    "y": 0.3884,
                    "Y": 28.23
                }
            },
            {
                "id": 63,
                "coordinates": {
                    "x": 0.4459,
                    "y": 0.3884,
                    "Y": 28.23
                }
            },
            {
                "id": 64,
                "coordinates": {
                    "x": 0.4459,
                    "y": 0.3884,
                    "Y": 28.23
                }
            },
            {
                "id": 65,
                "coordinates": {
                    "x": 0.4916,
                    "y": 0.3973,
                    "Y": 26.38
                }
            },
            {
                "id": 66,
                "coordinates": {
                    "x": 0.4916,
                    "y": 0.3973,
                    "Y": 26.38
                }
            },
            {
                "id": 67,
                "coordinates": {
                    "x": 0.2368,
                    "y": 0.2855,
                    "Y": 29.58
                }
            },
            {
                "id": 68,
                "coordinates": {
                    "x": 0.2368,
                    "y": 0.2855,
                    "Y": 29.58
                }
            },
            {
                "id": 69,
                "coordinates": {
                    "x": 0.2661,
                    "y": 0.3005,
                    "Y": 29.83
                }
            },
            {
                "id": 70,
                "coordinates": {
                    "x": 0.2661,
                    "y": 0.3005,
                    "Y": 29.83
                }
            },
            {
                "id": 71,
                "coordinates": {
                    "x": 0.2661,
                    "y": 0.3005,
                    "Y": 29.83
                }
            },
            {
                "id": 72,
                "coordinates": {
                    "x": 0.3007,
                    "y": 0.3189,
                    "Y": 30.26
                }
            },
            {
                "id": 73,
                "coordinates": {
                    "x": 0.3007,
                    "y": 0.3189,
                    "Y": 30.26
                }
            },
            {
                "id": 74,
                "coordinates": {
                    "x": 0.3007,
                    "y": 0.3189,
                    "Y": 30.26
                }
            },
            {
                "id": 75,
                "coordinates": {
                    "x": 0.3342,
                    "y": 0.334,
                    "Y": 27.95
                }
            },
            {
                "id": 76,
                "coordinates": {
                    "x": 0.3342,
                    "y": 0.334,
                    "Y": 27.95
                }
            },
            {
                "id": 77,
                "coordinates": {
                    "x": 0.3342,
                    "y": 0.334,
                    "Y": 27.95
                }
            },
            {
                "id": 78,
                "coordinates": {
                    "x": 0.3738,
                    "y": 0.3455,
                    "Y": 28.77
                }
            },
            {
                "id": 79,
                "coordinates": {
                    "x": 0.3738,
                    "y": 0.3455,
                    "Y": 28.77
                }
            },
            {
                "id": 80,
                "coordinates": {
                    "x": 0.3738,
                    "y": 0.3455,
                    "Y": 28.77
                }
            },
            {
                "id": 81,
                "coordinates": {
                    "x": 0.409,
                    "y": 0.357,
                    "Y": 28.49
                }
            },
            {
                "id": 82,
                "coordinates": {
                    "x": 0.409,
                    "y": 0.357,
                    "Y": 28.49
                }
            },
            {
                "id": 83,
                "coordinates": {
                    "x": 0.409,
                    "y": 0.357,
                    "Y": 28.49
                }
            },
            {
                "id": 84,
                "coordinates": {
                    "x": 0.4588,
                    "y": 0.3637,
                    "Y": 27.72
                }
            },
            {
                "id": 85,
                "coordinates": {
                    "x": 0.4588,
                    "y": 0.3637,
                    "Y": 27.72
                }
            },
            {
                "id": 86,
                "coordinates": {
                    "x": 0.4588,
                    "y": 0.3637,
                    "Y": 27.72
                }
            },
            {
                "id": 87,
                "coordinates": {
                    "x": 0.4869,
                    "y": 0.3649,
                    "Y": 28.29
                }
            },
            {
                "id": 88,
                "coordinates": {
                    "x": 0.2519,
                    "y": 0.2619,
                    "Y": 30.72
                }
            },
            {
                "id": 89,
                "coordinates": {
                    "x": 0.2797,
                    "y": 0.2814,
                    "Y": 30.73
                }
            },
            {
                "id": 90,
                "coordinates": {
                    "x": 0.2797,
                    "y": 0.2814,
                    "Y": 30.73
                }
            },
            {
                "id": 91,
                "coordinates": {
                    "x": 0.3064,
                    "y": 0.296,
                    "Y": 29.14
                }
            },
            {
                "id": 92,
                "coordinates": {
                    "x": 0.3064,
                    "y": 0.296,
                    "Y": 29.14
                }
            },
            {
                "id": 93,
                "coordinates": {
                    "x": 0.3064,
                    "y": 0.296,
                    "Y": 29.14
                }
            },
            {
                "id": 94,
                "coordinates": {
                    "x": 0.3406,
                    "y": 0.3133,
                    "Y": 29.18
                }
            },
            {
                "id": 95,
                "coordinates": {
                    "x": 0.3406,
                    "y": 0.3133,
                    "Y": 29.18
                }
            },
            {
                "id": 96,
                "coordinates": {
                    "x": 0.3406,
                    "y": 0.3133,
                    "Y": 29.18
                }
            },
            {
                "id": 97,
                "coordinates": {
                    "x": 0.3787,
                    "y": 0.3272,
                    "Y": 28.12
                }
            },
            {
                "id": 98,
                "coordinates": {
                    "x": 0.3787,
                    "y": 0.3272,
                    "Y": 28.12
                }
            },
            {
                "id": 99,
                "coordinates": {
                    "x": 0.3787,
                    "y": 0.3272,
                    "Y": 28.12
                }
            },
            {
                "id": 100,
                "coordinates": {
                    "x": 0.4199,
                    "y": 0.3336,
                    "Y": 28.5
                }
            },
            {
                "id": 101,
                "coordinates": {
                    "x": 0.4199,
                    "y": 0.3336,
                    "Y": 28.5
                }
            },
            {
                "id": 102,
                "coordinates": {
                    "x": 0.2938,
                    "y": 0.2605,
                    "Y": 29.86
                }
            },
            {
                "id": 103,
                "coordinates": {
                    "x": 0.3225,
                    "y": 0.274,
                    "Y": 28.77
                }
            },
            {
                "id": 104,
                "coordinates": {
                    "x": 0.3609,
                    "y": 0.287,
                    "Y": 28.65
                }
            },
            {
                "id": 105,
                "coordinates": {
                    "x": 0.515,
                    "y": 0.338,
                    "Y": 10.6
                }
            },
            {
                "id": 106,
                "coordinates": {
                    "x": 0.515,
                    "y": 0.338,
                    "Y": 10.6
                }
            },
            {
                "id": 107,
                "coordinates": {
                    "x": 0.515,
                    "y": 0.338,
                    "Y": 10.6
                }
            },
            {
                "id": 108,
                "coordinates": {
                    "x": 0.4916,
                    "y": 0.3477,
                    "Y": 10.3
                }
            },
            {
                "id": 109,
                "coordinates": {
                    "x": 0.4916,
                    "y": 0.3477,
                    "Y": 10.3
                }
            },
            {
                "id": 110,
                "coordinates": {
                    "x": 0.4424,
                    "y": 0.316,
                    "Y": 18.1
                }
            },
            {
                "id": 111,
                "coordinates": {
                    "x": 0.3708,
                    "y": 0.404,
                    "Y": 79.95
                }
            },
            {
                "id": 112,
                "coordinates": {
                    "x": 0.3708,
                    "y": 0.404,
                    "Y": 79.95
                }
            },
            {
                "id": 113,
                "coordinates": {
                    "x": 0.3708,
                    "y": 0.404,
                    "Y": 79.95
                }
            },
            {
                "id": 114,
                "coordinates": {
                    "x": 0.3896,
                    "y": 0.434,
                    "Y": 80.15
                }
            },
            {
                "id": 115,
                "coordinates": {
                    "x": 0.3896,
                    "y": 0.434,
                    "Y": 80.15
                }
            },
            {
                "id": 116,
                "coordinates": {
                    "x": 0.4054,
                    "y": 0.4334,
                    "Y": 58.27
                }
            },
            {
                "id": 117,
                "coordinates": {
                    "x": 0.2674,
                    "y": 0.3504,
                    "Y": 28.85
                }
            },
            {
                "id": 118,
                "coordinates": {
                    "x": 0.2674,
                    "y": 0.3504,
                    "Y": 28.85
                }
            },
            {
                "id": 119,
                "coordinates": {
                    "x": 0.2674,
                    "y": 0.3504,
                    "Y": 28.85
                }
            },
            {
                "id": 120,
                "coordinates": {
                    "x": 0.2434,
                    "y": 0.3636,
                    "Y": 30.07
                }
            },
            {
                "id": 121,
                "coordinates": {
                    "x": 0.2434,
                    "y": 0.3636,
                    "Y": 30.07
                }
            },
            {
                "id": 122,
                "coordinates": {
                    "x": 0.256,
                    "y": 0.3926,
                    "Y": 18.37
                }
            },
            {
                "id": 123,
                "coordinates": {
                    "x": 0.193,
                    "y": 0.1766,
                    "Y": 6.48
                }
            },
            {
                "id": 124,
                "coordinates": {
                    "x": 0.193,
                    "y": 0.1766,
                    "Y": 6.48
                }
            },
            {
                "id": 125,
                "coordinates": {
                    "x": 0.193,
                    "y": 0.1766,
                    "Y": 6.48
                }
            },
            {
                "id": 126,
                "coordinates": {
                    "x": 0.2248,
                    "y": 0.2276,
                    "Y": 6.04
                }
            },
            {
                "id": 127,
                "coordinates": {
                    "x": 0.2248,
                    "y": 0.2276,
                    "Y": 6.04
                }
            },
            {
                "id": 128,
                "coordinates": {
                    "x": 0.2136,
                    "y": 0.2379,
                    "Y": 11.74
                }
            }
        ],
        "color2": [
            {
                "id": 1,
                "coordinates": {
                    "x": 0.2952,
                    "y": 0.4786,
                    "Y": 29.96
                }
            },
            {
                "id": 2,
                "coordinates": {
                    "x": 0.3466,
                    "y": 0.4899,
                    "Y": 29.28
                }
            },
            {
                "id": 3,
                "coordinates": {
                    "x": 0.3466,
                    "y": 0.4899,
                    "Y": 29.28
                }
            },
            {
                "id": 4,
                "coordinates": {
                    "x": 0.2627,
                    "y": 0.4254,
                    "Y": 29.58
                }
            },
            {
                "id": 5,
                "coordinates": {
                    "x": 0.3039,
                    "y": 0.4358,
                    "Y": 27.84
                }
            },
            {
                "id": 6,
                "coordinates": {
                    "x": 0.3949,
                    "y": 0.4897,
                    "Y": 27.15
                }
            },
            {
                "id": 7,
                "coordinates": {
                    "x": 0.3039,
                    "y": 0.4358,
                    "Y": 27.84
                }
            },
            {
                "id": 8,
                "coordinates": {
                    "x": 0.355,
                    "y": 0.4477,
                    "Y": 27.16
                }
            },
            {
                "id": 9,
                "coordinates": {
                    "x": 0.355,
                    "y": 0.4477,
                    "Y": 27.16
                }
            },
            {
                "id": 10,
                "coordinates": {
                    "x": 0.3933,
                    "y": 0.4506,
                    "Y": 25.06
                }
            },
            {
                "id": 11,
                "coordinates": {
                    "x": 0.3039,
                    "y": 0.4358,
                    "Y": 27.84
                }
            },
            {
                "id": 12,
                "coordinates": {
                    "x": 0.2376,
                    "y": 0.3652,
                    "Y": 29.51
                }
            },
            {
                "id": 13,
                "coordinates": {
                    "x": 0.2747,
                    "y": 0.3785,
                    "Y": 28.26
                }
            },
            {
                "id": 14,
                "coordinates": {
                    "x": 0.355,
                    "y": 0.4477,
                    "Y": 27.16
                }
            },
            {
                "id": 15,
                "coordinates": {
                    "x": 0.2747,
                    "y": 0.3785,
                    "Y": 28.26
                }
            },
            {
                "id": 16,
                "coordinates": {
                    "x": 0.3159,
                    "y": 0.3928,
                    "Y": 27.56
                }
            },
            {
                "id": 17,
                "coordinates": {
                    "x": 0.3933,
                    "y": 0.4506,
                    "Y": 25.06
                }
            },
            {
                "id": 18,
                "coordinates": {
                    "x": 0.3159,
                    "y": 0.3928,
                    "Y": 27.56
                }
            },
            {
                "id": 19,
                "coordinates": {
                    "x": 0.3616,
                    "y": 0.4073,
                    "Y": 28.68
                }
            },
            {
                "id": 20,
                "coordinates": {
                    "x": 0.4469,
                    "y": 0.4595,
                    "Y": 26.79
                }
            },
            {
                "id": 21,
                "coordinates": {
                    "x": 0.3616,
                    "y": 0.4073,
                    "Y": 28.68
                }
            },
            {
                "id": 22,
                "coordinates": {
                    "x": 0.4025,
                    "y": 0.4161,
                    "Y": 27.55
                }
            },
            {
                "id": 23,
                "coordinates": {
                    "x": 0.4025,
                    "y": 0.4161,
                    "Y": 27.55
                }
            },
            {
                "id": 24,
                "coordinates": {
                    "x": 0.4475,
                    "y": 0.4224,
                    "Y": 27.3
                }
            },
            {
                "id": 25,
                "coordinates": {
                    "x": 0.2747,
                    "y": 0.3785,
                    "Y": 28.26
                }
            },
            {
                "id": 26,
                "coordinates": {
                    "x": 0.2305,
                    "y": 0.3215,
                    "Y": 30.03
                }
            },
            {
                "id": 27,
                "coordinates": {
                    "x": 0.2531,
                    "y": 0.3311,
                    "Y": 29.53
                }
            },
            {
                "id": 28,
                "coordinates": {
                    "x": 0.3159,
                    "y": 0.3928,
                    "Y": 27.56
                }
            },
            {
                "id": 29,
                "coordinates": {
                    "x": 0.2531,
                    "y": 0.3311,
                    "Y": 29.53
                }
            },
            {
                "id": 30,
                "coordinates": {
                    "x": 0.2863,
                    "y": 0.3418,
                    "Y": 28.39
                }
            },
            {
                "id": 31,
                "coordinates": {
                    "x": 0.3616,
                    "y": 0.4073,
                    "Y": 28.68
                }
            },
            {
                "id": 32,
                "coordinates": {
                    "x": 0.2863,
                    "y": 0.3418,
                    "Y": 28.39
                }
            },
            {
                "id": 33,
                "coordinates": {
                    "x": 0.3247,
                    "y": 0.3584,
                    "Y": 28.84
                }
            },
            {
                "id": 34,
                "coordinates": {
                    "x": 0.4025,
                    "y": 0.4161,
                    "Y": 27.55
                }
            },
            {
                "id": 35,
                "coordinates": {
                    "x": 0.3247,
                    "y": 0.3584,
                    "Y": 28.84
                }
            },
            {
                "id": 36,
                "coordinates": {
                    "x": 0.3627,
                    "y": 0.3704,
                    "Y": 28.75
                }
            },
            {
                "id": 37,
                "coordinates": {
                    "x": 0.4475,
                    "y": 0.4224,
                    "Y": 27.3
                }
            },
            {
                "id": 38,
                "coordinates": {
                    "x": 0.3627,
                    "y": 0.3704,
                    "Y": 28.75
                }
            },
            {
                "id": 39,
                "coordinates": {
                    "x": 0.4068,
                    "y": 0.384,
                    "Y": 28.21
                }
            },
            {
                "id": 40,
                "coordinates": {
                    "x": 0.4833,
                    "y": 0.4221,
                    "Y": 26.54
                }
            },
            {
                "id": 41,
                "coordinates": {
                    "x": 0.4068,
                    "y": 0.384,
                    "Y": 28.21
                }
            },
            {
                "id": 42,
                "coordinates": {
                    "x": 0.4459,
                    "y": 0.3884,
                    "Y": 28.23
                }
            },
            {
                "id": 43,
                "coordinates": {
                    "x": 0.4459,
                    "y": 0.3884,
                    "Y": 28.23
                }
            },
            {
                "id": 44,
                "coordinates": {
                    "x": 0.4916,
                    "y": 0.3973,
                    "Y": 26.38
                }
            },
            {
                "id": 45,
                "coordinates": {
                    "x": 0.2531,
                    "y": 0.3311,
                    "Y": 29.53
                }
            },
            {
                "id": 46,
                "coordinates": {
                    "x": 0.2368,
                    "y": 0.2855,
                    "Y": 29.58
                }
            },
            {
                "id": 47,
                "coordinates": {
                    "x": 0.2863,
                    "y": 0.3418,
                    "Y": 28.39
                }
            },
            {
                "id": 48,
                "coordinates": {
                    "x": 0.2368,
                    "y": 0.2855,
                    "Y": 29.58
                }
            },
            {
                "id": 49,
                "coordinates": {
                    "x": 0.2661,
                    "y": 0.3005,
                    "Y": 29.83
                }
            },
            {
                "id": 50,
                "coordinates": {
                    "x": 0.3247,
                    "y": 0.3584,
                    "Y": 28.84
                }
            },
            {
                "id": 51,
                "coordinates": {
                    "x": 0.2661,
                    "y": 0.3005,
                    "Y": 29.83
                }
            },
            {
                "id": 52,
                "coordinates": {
                    "x": 0.3007,
                    "y": 0.3189,
                    "Y": 30.26
                }
            },
            {
                "id": 53,
                "coordinates": {
                    "x": 0.3627,
                    "y": 0.3704,
                    "Y": 28.75
                }
            },
            {
                "id": 54,
                "coordinates": {
                    "x": 0.3007,
                    "y": 0.3189,
                    "Y": 30.26
                }
            },
            {
                "id": 55,
                "coordinates": {
                    "x": 0.3342,
                    "y": 0.334,
                    "Y": 27.95
                }
            },
            {
                "id": 56,
                "coordinates": {
                    "x": 0.4068,
                    "y": 0.384,
                    "Y": 28.21
                }
            },
            {
                "id": 57,
                "coordinates": {
                    "x": 0.3342,
                    "y": 0.334,
                    "Y": 27.95
                }
            },
            {
                "id": 58,
                "coordinates": {
                    "x": 0.3738,
                    "y": 0.3455,
                    "Y": 28.77
                }
            },
            {
                "id": 59,
                "coordinates": {
                    "x": 0.4459,
                    "y": 0.3884,
                    "Y": 28.23
                }
            },
            {
                "id": 60,
                "coordinates": {
                    "x": 0.3738,
                    "y": 0.3455,
                    "Y": 28.77
                }
            },
            {
                "id": 61,
                "coordinates": {
                    "x": 0.409,
                    "y": 0.357,
                    "Y": 28.49
                }
            },
            {
                "id": 62,
                "coordinates": {
                    "x": 0.4916,
                    "y": 0.3973,
                    "Y": 26.38
                }
            },
            {
                "id": 63,
                "coordinates": {
                    "x": 0.409,
                    "y": 0.357,
                    "Y": 28.49
                }
            },
            {
                "id": 64,
                "coordinates": {
                    "x": 0.4588,
                    "y": 0.3637,
                    "Y": 27.72
                }
            },
            {
                "id": 65,
                "coordinates": {
                    "x": 0.4588,
                    "y": 0.3637,
                    "Y": 27.72
                }
            },
            {
                "id": 66,
                "coordinates": {
                    "x": 0.4869,
                    "y": 0.3649,
                    "Y": 28.29
                }
            },
            {
                "id": 67,
                "coordinates": {
                    "x": 0.2661,
                    "y": 0.3005,
                    "Y": 29.83
                }
            },
            {
                "id": 68,
                "coordinates": {
                    "x": 0.2519,
                    "y": 0.2619,
                    "Y": 30.72
                }
            },
            {
                "id": 69,
                "coordinates": {
                    "x": 0.3007,
                    "y": 0.3189,
                    "Y": 30.26
                }
            },
            {
                "id": 70,
                "coordinates": {
                    "x": 0.2519,
                    "y": 0.2619,
                    "Y": 30.72
                }
            },
            {
                "id": 71,
                "coordinates": {
                    "x": 0.2797,
                    "y": 0.2814,
                    "Y": 30.73
                }
            },
            {
                "id": 72,
                "coordinates": {
                    "x": 0.3342,
                    "y": 0.334,
                    "Y": 27.95
                }
            },
            {
                "id": 73,
                "coordinates": {
                    "x": 0.2797,
                    "y": 0.2814,
                    "Y": 30.73
                }
            },
            {
                "id": 74,
                "coordinates": {
                    "x": 0.3064,
                    "y": 0.296,
                    "Y": 29.14
                }
            },
            {
                "id": 75,
                "coordinates": {
                    "x": 0.3738,
                    "y": 0.3455,
                    "Y": 28.77
                }
            },
            {
                "id": 76,
                "coordinates": {
                    "x": 0.3064,
                    "y": 0.296,
                    "Y": 29.14
                }
            },
            {
                "id": 77,
                "coordinates": {
                    "x": 0.3406,
                    "y": 0.3133,
                    "Y": 29.18
                }
            },
            {
                "id": 78,
                "coordinates": {
                    "x": 0.409,
                    "y": 0.357,
                    "Y": 28.49
                }
            },
            {
                "id": 79,
                "coordinates": {
                    "x": 0.3406,
                    "y": 0.3133,
                    "Y": 29.18
                }
            },
            {
                "id": 80,
                "coordinates": {
                    "x": 0.3787,
                    "y": 0.3272,
                    "Y": 28.12
                }
            },
            {
                "id": 81,
                "coordinates": {
                    "x": 0.4588,
                    "y": 0.3637,
                    "Y": 27.72
                }
            },
            {
                "id": 82,
                "coordinates": {
                    "x": 0.3787,
                    "y": 0.3272,
                    "Y": 28.12
                }
            },
            {
                "id": 83,
                "coordinates": {
                    "x": 0.4199,
                    "y": 0.3336,
                    "Y": 28.5
                }
            },
            {
                "id": 84,
                "coordinates": {
                    "x": 0.4869,
                    "y": 0.3649,
                    "Y": 28.29
                }
            },
            {
                "id": 85,
                "coordinates": {
                    "x": 0.4199,
                    "y": 0.3336,
                    "Y": 28.5
                }
            },
            {
                "id": 86,
                "coordinates": {
                    "x": 0.4555,
                    "y": 0.3383,
                    "Y": 28.14
                }
            },
            {
                "id": 87,
                "coordinates": {
                    "x": 0.4555,
                    "y": 0.3383,
                    "Y": 28.14
                }
            },
            {
                "id": 88,
                "coordinates": {
                    "x": 0.2797,
                    "y": 0.2814,
                    "Y": 30.73
                }
            },
            {
                "id": 89,
                "coordinates": {
                    "x": 0.3064,
                    "y": 0.296,
                    "Y": 29.14
                }
            },
            {
                "id": 90,
                "coordinates": {
                    "x": 0.2938,
                    "y": 0.2605,
                    "Y": 29.86
                }
            },
            {
                "id": 91,
                "coordinates": {
                    "x": 0.3406,
                    "y": 0.3133,
                    "Y": 29.18
                }
            },
            {
                "id": 92,
                "coordinates": {
                    "x": 0.2938,
                    "y": 0.2605,
                    "Y": 29.86
                }
            },
            {
                "id": 93,
                "coordinates": {
                    "x": 0.3225,
                    "y": 0.274,
                    "Y": 28.77
                }
            },
            {
                "id": 94,
                "coordinates": {
                    "x": 0.3787,
                    "y": 0.3272,
                    "Y": 28.12
                }
            },
            {
                "id": 95,
                "coordinates": {
                    "x": 0.3225,
                    "y": 0.274,
                    "Y": 28.77
                }
            },
            {
                "id": 96,
                "coordinates": {
                    "x": 0.3609,
                    "y": 0.287,
                    "Y": 28.65
                }
            },
            {
                "id": 97,
                "coordinates": {
                    "x": 0.4199,
                    "y": 0.3336,
                    "Y": 28.5
                }
            },
            {
                "id": 98,
                "coordinates": {
                    "x": 0.3609,
                    "y": 0.287,
                    "Y": 28.65
                }
            },
            {
                "id": 99,
                "coordinates": {
                    "x": 0.3866,
                    "y": 0.294,
                    "Y": 27.92
                }
            },
            {
                "id": 100,
                "coordinates": {
                    "x": 0.4555,
                    "y": 0.3383,
                    "Y": 28.14
                }
            },
            {
                "id": 101,
                "coordinates": {
                    "x": 0.3866,
                    "y": 0.294,
                    "Y": 27.92
                }
            },
            {
                "id": 102,
                "coordinates": {
                    "x": 0.3225,
                    "y": 0.274,
                    "Y": 28.77
                }
            },
            {
                "id": 103,
                "coordinates": {
                    "x": 0.3609,
                    "y": 0.287,
                    "Y": 28.65
                }
            },
            {
                "id": 104,
                "coordinates": {
                    "x": 0.3866,
                    "y": 0.294,
                    "Y": 27.92
                }
            },
            {
                "id": 105,
                "coordinates": {
                    "x": 0.4916,
                    "y": 0.3477,
                    "Y": 10.3
                }
            },
            {
                "id": 106,
                "coordinates": {
                    "x": 0.4424,
                    "y": 0.316,
                    "Y": 18.1
                }
            },
            {
                "id": 107,
                "coordinates": {
                    "x": 0.4874,
                    "y": 0.3661,
                    "Y": 17.27
                }
            },
            {
                "id": 108,
                "coordinates": {
                    "x": 0.4424,
                    "y": 0.316,
                    "Y": 18.1
                }
            },
            {
                "id": 109,
                "coordinates": {
                    "x": 0.4874,
                    "y": 0.3661,
                    "Y": 17.27
                }
            },
            {
                "id": 110,
                "coordinates": {
                    "x": 0.4874,
                    "y": 0.3661,
                    "Y": 17.27
                }
            },
            {
                "id": 111,
                "coordinates": {
                    "x": 0.3896,
                    "y": 0.434,
                    "Y": 80.15
                }
            },
            {
                "id": 112,
                "coordinates": {
                    "x": 0.4054,
                    "y": 0.4334,
                    "Y": 58.27
                }
            },
            {
                "id": 113,
                "coordinates": {
                    "x": 0.3868,
                    "y": 0.4409,
                    "Y": 58.85
                }
            },
            {
                "id": 114,
                "coordinates": {
                    "x": 0.4054,
                    "y": 0.4334,
                    "Y": 58.27
                }
            },
            {
                "id": 115,
                "coordinates": {
                    "x": 0.3868,
                    "y": 0.4409,
                    "Y": 58.85
                }
            },
            {
                "id": 116,
                "coordinates": {
                    "x": 0.3868,
                    "y": 0.4409,
                    "Y": 58.85
                }
            },
            {
                "id": 117,
                "coordinates": {
                    "x": 0.2434,
                    "y": 0.3636,
                    "Y": 30.07
                }
            },
            {
                "id": 118,
                "coordinates": {
                    "x": 0.256,
                    "y": 0.3926,
                    "Y": 18.37
                }
            },
            {
                "id": 119,
                "coordinates": {
                    "x": 0.2265,
                    "y": 0.3406,
                    "Y": 18.7
                }
            },
            {
                "id": 120,
                "coordinates": {
                    "x": 0.256,
                    "y": 0.3926,
                    "Y": 18.37
                }
            },
            {
                "id": 121,
                "coordinates": {
                    "x": 0.2265,
                    "y": 0.3406,
                    "Y": 18.7
                }
            },
            {
                "id": 122,
                "coordinates": {
                    "x": 0.2265,
                    "y": 0.3406,
                    "Y": 18.7
                }
            },
            {
                "id": 123,
                "coordinates": {
                    "x": 0.2248,
                    "y": 0.2276,
                    "Y": 6.04
                }
            },
            {
                "id": 124,
                "coordinates": {
                    "x": 0.2136,
                    "y": 0.2379,
                    "Y": 11.74
                }
            },
            {
                "id": 125,
                "coordinates": {
                    "x": 0.2432,
                    "y": 0.2212,
                    "Y": 10.98
                }
            },
            {
                "id": 126,
                "coordinates": {
                    "x": 0.2136,
                    "y": 0.2379,
                    "Y": 11.74
                }
            },
            {
                "id": 127,
                "coordinates": {
                    "x": 0.2432,
                    "y": 0.2212,
                    "Y": 10.98
                }
            },
            {
                "id": 128,
                "coordinates": {
                    "x": 0.2432,
                    "y": 0.2212,
                    "Y": 10.98
                }
            }
        ],
        "distances": [
            {
                "id": 1,
                "value": 2.311
            },
            {
                "id": 2,
                "value": 2.608
            },
            {
                "id": 3,
                "value": 2.176
            },
            {
                "id": 4,
                "value": 2.16
            },
            {
                "id": 5,
                "value": 1.818
            },
            {
                "id": 6,
                "value": 2.569
            },
            {
                "id": 7,
                "value": 2.788
            },
            {
                "id": 8,
                "value": 2.038
            },
            {
                "id": 9,
                "value": 1.877
            },
            {
                "id": 10,
                "value": 2.127
            },
            {
                "id": 11,
                "value": 2.268
            },
            {
                "id": 12,
                "value": 2.602
            },
            {
                "id": 13,
                "value": 1.746
            },
            {
                "id": 14,
                "value": 2.039
            },
            {
                "id": 15,
                "value": 2.054
            },
            {
                "id": 16,
                "value": 1.24
            },
            {
                "id": 17,
                "value": 2.234
            },
            {
                "id": 18,
                "value": 1.56
            },
            {
                "id": 19,
                "value": 1.957
            },
            {
                "id": 20,
                "value": 2.944
            },
            {
                "id": 21,
                "value": 1.706
            },
            {
                "id": 22,
                "value": 2.525
            },
            {
                "id": 23,
                "value": 2.133
            },
            {
                "id": 24,
                "value": 2.727
            },
            {
                "id": 25,
                "value": 1.705
            },
            {
                "id": 26,
                "value": 2.537
            },
            {
                "id": 27,
                "value": 2.177
            },
            {
                "id": 28,
                "value": 2.122
            },
            {
                "id": 29,
                "value": 2.728
            },
            {
                "id": 30,
                "value": 1.655
            },
            {
                "id": 31,
                "value": 1.943
            },
            {
                "id": 32,
                "value": 2.279
            },
            {
                "id": 33,
                "value": 1.972
            },
            {
                "id": 34,
                "value": 2.122
            },
            {
                "id": 35,
                "value": 1.86
            },
            {
                "id": 36,
                "value": 1.994
            },
            {
                "id": 37,
                "value": 2.462
            },
            {
                "id": 38,
                "value": 1.689
            },
            {
                "id": 39,
                "value": 2.391
            },
            {
                "id": 40,
                "value": 1.739
            },
            {
                "id": 41,
                "value": 2.312
            },
            {
                "id": 42,
                "value": 2.436
            },
            {
                "id": 43,
                "value": 2.315
            },
            {
                "id": 44,
                "value": 2.538
            },
            {
                "id": 45,
                "value": 1.709
            },
            {
                "id": 46,
                "value": 3.399
            },
            {
                "id": 47,
                "value": 2.247
            },
            {
                "id": 48,
                "value": 3.345
            },
            {
                "id": 49,
                "value": 3.223
            },
            {
                "id": 50,
                "value": 2.342
            },
            {
                "id": 51,
                "value": 3.019
            },
            {
                "id": 52,
                "value": 2.588
            },
            {
                "id": 53,
                "value": 2.257
            },
            {
                "id": 54,
                "value": 2.459
            },
            {
                "id": 55,
                "value": 2.387
            },
            {
                "id": 56,
                "value": 1.599
            },
            {
                "id": 57,
                "value": 1.792
            },
            {
                "id": 58,
                "value": 2.358
            },
            {
                "id": 59,
                "value": 1.409
            },
            {
                "id": 60,
                "value": 1.643
            },
            {
                "id": 61,
                "value": 2.16
            },
            {
                "id": 62,
                "value": 1.846
            },
            {
                "id": 63,
                "value": 1.872
            },
            {
                "id": 64,
                "value": 2.507
            },
            {
                "id": 65,
                "value": 2.907
            },
            {
                "id": 66,
                "value": 2.974
            },
            {
                "id": 67,
                "value": 2.232
            },
            {
                "id": 68,
                "value": 3.389
            },
            {
                "id": 69,
                "value": 2.126
            },
            {
                "id": 70,
                "value": 3.001
            },
            {
                "id": 71,
                "value": 2.74
            },
            {
                "id": 72,
                "value": 2
            },
            {
                "id": 73,
                "value": 2.734
            },
            {
                "id": 74,
                "value": 2.513
            },
            {
                "id": 75,
                "value": 2.014
            },
            {
                "id": 76,
                "value": 2.73
            },
            {
                "id": 77,
                "value": 1.957
            },
            {
                "id": 78,
                "value": 1.369
            },
            {
                "id": 79,
                "value": 2.071
            },
            {
                "id": 80,
                "value": 1.496
            },
            {
                "id": 81,
                "value": 2.052
            },
            {
                "id": 82,
                "value": 2.483
            },
            {
                "id": 83,
                "value": 2.039
            },
            {
                "id": 84,
                "value": 1.218
            },
            {
                "id": 85,
                "value": 2.519
            },
            {
                "id": 86,
                "value": 2.487
            },
            {
                "id": 87,
                "value": 2.564
            },
            {
                "id": 88,
                "value": 2.709
            },
            {
                "id": 89,
                "value": 1.805
            },
            {
                "id": 90,
                "value": 2.435
            },
            {
                "id": 91,
                "value": 1.889
            },
            {
                "id": 92,
                "value": 2.15
            },
            {
                "id": 93,
                "value": 2.372
            },
            {
                "id": 94,
                "value": 1.915
            },
            {
                "id": 95,
                "value": 2.853
            },
            {
                "id": 96,
                "value": 2.024
            },
            {
                "id": 97,
                "value": 1.489
            },
            {
                "id": 98,
                "value": 2.436
            },
            {
                "id": 99,
                "value": 2.525
            },
            {
                "id": 100,
                "value": 1.457
            },
            {
                "id": 101,
                "value": 2.945
            },
            {
                "id": 102,
                "value": 2.242
            },
            {
                "id": 103,
                "value": 2.093
            },
            {
                "id": 104,
                "value": 1.275
            },
            {
                "id": 105,
                "value": 1.611
            },
            {
                "id": 106,
                "value": 3.497
            },
            {
                "id": 107,
                "value": 3.15
            },
            {
                "id": 108,
                "value": 3.538
            },
            {
                "id": 109,
                "value": 2.59
            },
            {
                "id": 110,
                "value": 3.253
            },
            {
                "id": 111,
                "value": 2.498
            },
            {
                "id": 112,
                "value": 3.365
            },
            {
                "id": 113,
                "value": 3.701
            },
            {
                "id": 114,
                "value": 2.773
            },
            {
                "id": 115,
                "value": 2.61
            },
            {
                "id": 116,
                "value": 2.253
            },
            {
                "id": 117,
                "value": 1.733
            },
            {
                "id": 118,
                "value": 3.375
            },
            {
                "id": 119,
                "value": 2.804
            },
            {
                "id": 120,
                "value": 3.803
            },
            {
                "id": 121,
                "value": 3.375
            },
            {
                "id": 122,
                "value": 2.508
            },
            {
                "id": 123,
                "value": 1.835
            },
            {
                "id": 124,
                "value": 2.467
            },
            {
                "id": 125,
                "value": 3.151
            },
            {
                "id": 126,
                "value": 2.641
            },
            {
                "id": 127,
                "value": 2.936
            },
            {
                "id": 128,
                "value": 3.008
            }
        ]
    }
}